eeg_uhb/__init__.py
eeg_uhb/acquisition.py
eeg_uhb/errors.py
eeg_uhb/io.py
eeg_uhb/processing.py
eeg_uhb/resources/Fuzzy_Systems.pkl
eeg_uhb/resources/__init__.py
eeg_uhb/resources/coefficient_filters_dict.pkl
eeg_uhb/utils/EEGStressDetector.py
eeg_uhb/utils/__init__.py
eeg_uhb-0.1.9.dist-info/METADATA
eeg_uhb-0.1.9.dist-info/WHEEL
eeg_uhb-0.1.9.dist-info/top_level.txt
eeg_uhb-0.1.9.dist-info/RECORD
