Metadata-Version: 2.4
Name: eeg-uhb
Version: 0.1.9
Summary: Librería modular para adquisición y procesamiento EEG de UHB
Author-email: Amaury Santiago Horta <asantiagoh2300@alumno.ipn.mx>
Project-URL: Homepage, https://github.com/IngAmaury/EEG_UHB_LIBRARY
Classifier: Programming Language :: Python :: 3
Classifier: Programming Language :: Python :: 3.8
Classifier: Programming Language :: Python :: 3.9
Classifier: Programming Language :: Python :: 3.10
Classifier: Programming Language :: Python :: 3.11
Classifier: License :: Other/Proprietary License
Classifier: Operating System :: OS Independent
Classifier: Intended Audience :: Science/Research
Classifier: Topic :: Scientific/Engineering :: Bio-Informatics
Requires-Python: >=3.8
Requires-Dist: networkx>=3.0
Requires-Dist: numpy==1.26.4
Requires-Dist: packaging>=20.0
Requires-Dist: pylsl==1.15.0
Requires-Dist: scikit-fuzzy==0.5.0
Requires-Dist: scipy>=1.13.1
